AUTHORS
ChangeLog
README.md
requirements.txt
setup.cfg
setup.py
test-requirements.txt
osmo/__init__.py
osmo/base.py
osmo/db.py
osmo/log.py
osmo/util.py
osmo/wsgi.py
osmo.egg-info/PKG-INFO
osmo.egg-info/SOURCES.txt
osmo.egg-info/dependency_links.txt
osmo.egg-info/not-zip-safe
osmo.egg-info/pbr.json
osmo.egg-info/requires.txt
osmo.egg-info/top_level.txt